utils_b_infra/__init__.py
utils_b_infra/ai.py
utils_b_infra/cache.py
utils_b_infra/generic.py
utils_b_infra/logging.py
utils_b_infra/pandas.py
utils_b_infra/services.py
utils_b_infra/translation.py
utils_b_infra/caching/__init__.py
utils_b_infra/caching/coder.py
utils_b_infra/caching/config.py
utils_b_infra/caching/utils.py
utils_b_infra/caching/backends/__init__.py
utils_b_infra/caching/backends/base.py
utils_b_infra/caching/backends/mongocache.py
utils_b_infra/caching/backends/rediscache.py
utils_b_infra/caching/backends/simplecache.py
utils_b_infra-1.3.25.dist-info/LICENSE
utils_b_infra-1.3.25.dist-info/METADATA
utils_b_infra-1.3.25.dist-info/WHEEL
utils_b_infra-1.3.25.dist-info/top_level.txt
utils_b_infra-1.3.25.dist-info/RECORD
