Metadata-Version: 2.1
Name: utils-b-infra
Version: 1.3.25
Summary: A collection of utility functions and classes for Python projects.
Home-page: https://github.com/Fahadukr/utils-b-infra
Author: Fahad Mawlood
Author-email: fahadukr@gmail.com
License: UNKNOWN
Platform: UNKNOWN
Classifier: Programming Language :: Python :: 3
Classifier: License :: OSI Approved :: MIT License
Classifier: Operating System :: OS Independent
Requires-Python: >=3.10
Requires-Dist: SQLAlchemy
Requires-Dist: pandas
Requires-Dist: numpy<2.0.0
Requires-Dist: openai>=1.74.0
Requires-Dist: redis
Requires-Dist: pymongo
Requires-Dist: pendulum
Requires-Dist: slack-sdk
Requires-Dist: tiktoken
Requires-Dist: google-api-python-client
Requires-Dist: google-auth-httplib2
Requires-Dist: google-auth-oauthlib
Requires-Dist: Pillow
Requires-Dist: pdf2image
Requires-Dist: pydub
Provides-Extra: translation
Requires-Dist: google-cloud-translate>=3.12.0; extra == "translation"
Requires-Dist: deepl; extra == "translation"
